.gitignore
LICENSE
README.rst
setup.py
.circleci/config.yml
docker/singleuser/Dockerfile
girder_jupyterhub/__init__.py
girder_jupyterhub.egg-info/PKG-INFO
girder_jupyterhub.egg-info/SOURCES.txt
girder_jupyterhub.egg-info/dependency_links.txt
girder_jupyterhub.egg-info/requires.txt
girder_jupyterhub.egg-info/top_level.txt
girder_jupyterhub/auth/__init__.py
girder_jupyterhub/auth/girderauthenticator.py