Metadata-Version: 1.1
Name: girder-jupyterhub
Version: 0.1.1.dev7
Summary: A JupyterHub authenticator for Girder tokens
Home-page: https://github.com/cjh1/girder_jupyterhub
Author: Kitware Inc
Author-email: kitware@kitware.com
License: BSD 3-Clause
Keywords: jupyter girder authentication data management
Platform: UNKNOWN
Classifier: Development Status :: 3 - Alpha
Classifier: License :: OSI Approved :: BSD License
Classifier: Programming Language :: Python :: 2.7
Classifier: Programming Language :: Python :: 3.6
